{
  "root": {
    "boundingVolume": {
      "region": [
        3.1002858331948912607, -0.67531925092816957878, 3.1003982511000760525,
        -0.67523452543215622956, 116.38199699204415083, 217.56935203354805708
      ]
    },
    "refine": "REPLACE",
    "geometricError": 122.301826,
    "content": {
      "uri": "mesh_1774.b3dm",
      "boundingVolume": {
        "region": [
          3.1002858331948912607, -0.67531925092816957878, 3.1003982511000760525,
          -0.67523452543215622956, 116.38199699204415083, 217.56935203354805708
        ]
      }
    },
    "children": [
      {
        "boundingVolume": {
          "region": [
            3.1002858584439985101, -0.67531925038486972923, 3.10039825109751499,
            -0.67523470479128577804, 117.66279549431055784,
            217.56935067009180784
          ]
        },
        "refine": "REPLACE",
        "geometricError": 8.608414,
        "content": {
          "uri": "mesh_1775.b3dm",
          "boundingVolume": {
            "region": [
              3.1002858584439985101, -0.67531925038486972923,
              3.10039825109751499, -0.67523470479128577804,
              117.66279549431055784, 217.56935067009180784
            ]
          }
        },
        "children": [
          {
            "boundingVolume": {
              "region": [
                3.100293748696337115, -0.67531836673337575228,
                3.1003359999944386516, -0.67528690561160620298,
                140.79509958904236555, 212.5119346110150218
              ]
            },
            "refine": "REPLACE",
            "geometricError": 4.393863,
            "content": {
              "uri": "mesh_1776.b3dm",
              "boundingVolume": {
                "region": [
                  3.100293748696337115, -0.67531836673337575228,
                  3.1003359999944386516, -0.67528690561160620298,
                  140.79509958904236555, 212.5119346110150218
                ]
              }
            },
            "children": [
              {
                "boundingVolume": {
                  "region": [
                    3.1002975572235396129, -0.67531787974833112909,
                    3.1003049158641986516, -0.67531214095336566938,
                    161.43135764636099339, 200.00544669665396214
                  ]
                },
                "refine": "REPLACE",
                "geometricError": 3.047103,
                "content": {
                  "uri": "mesh_1777.b3dm",
                  "boundingVolume": {
                    "region": [
                      3.1002975572235396129, -0.67531787974833112909,
                      3.1003049158641986516, -0.67531214095336566938,
                      161.43135764636099339, 200.00544669665396214
                    ]
                  }
                },
                "children": [
                  {
                    "boundingVolume": {
                      "region": [
                        3.1002976431553439518, -0.67531783307638060254,
                        3.1003048407720541491, -0.67531222173493687944,
                        161.76320634968578815, 200.0054472554475069
                      ]
                    },
                    "refine": "REPLACE",
                    "geometricError": 1.52129,
                    "content": {
                      "uri": "mesh_1778.b3dm",
                      "boundingVolume": {
                        "region": [
                          3.1002976431553439518, -0.67531783307638060254,
                          3.1003048407720541491, -0.67531222173493687944,
                          161.76320634968578815, 200.0054472554475069
                        ]
                      }
                    }
                  }
                ]
              },
              {
                "boundingVolume": {
                  "region": [
                    3.1002947325861320849, -0.67531498437094028553,
                    3.1003291063886870838, -0.67528821857300036502,
                    147.28729268908500671, 211.80881521105766296
                  ]
                },
                "refine": "REPLACE",
                "geometricError": 3.042829,
                "content": {
                  "uri": "mesh_1779.b3dm",
                  "boundingVolume": {
                    "region": [
                      3.1002947325861320849, -0.67531498437094028553,
                      3.1003291063886870838, -0.67528821857300036502,
                      147.28729268908500671, 211.80881521105766296
                    ]
                  }
                },
                "children": [
                  {
                    "boundingVolume": {
                      "region": [
                        3.1002967636105562832, -0.67531410147800230437,
                        3.1003133185148099571, -0.67530135831426718607,
                        147.47881980799138546, 209.33222862146794796
                      ]
                    },
                    "refine": "REPLACE",
                    "geometricError": 1.520146,
                    "content": {
                      "uri": "mesh_1780.b3dm",
                      "boundingVolume": {
                        "region": [
                          3.1002967636105562832, -0.67531410147800230437,
                          3.1003133185148099571, -0.67530135831426718607,
                          147.47881980799138546, 209.33222862146794796
                        ]
                      }
                    }
                  },
                  {
                    "boundingVolume": {
                      "region": [
                        3.1003126672418108711, -0.67530546588466533464,
                        3.100319627068533368, -0.67530003803993099432,
                        187.50002257712185383, 203.82905166037380695
                      ]
                    },
                    "refine": "REPLACE",
                    "geometricError": 1.522641,
                    "content": {
                      "uri": "mesh_1781.b3dm",
                      "boundingVolume": {
                        "region": [
                          3.1003126672418108711, -0.67530546588466533464,
                          3.100319627068533368, -0.67530003803993099432,
                          187.50002257712185383, 203.82905166037380695
                        ]
                      }
                    }
                  },
                  {
                    "boundingVolume": {
                      "region": [
                        3.1002963415155386784, -0.67530157133270896086,
                        3.1003128962385302358, -0.67528882818005597777,
                        151.18851443007588387, 194.63800783827900887
                      ]
                    },
                    "refine": "REPLACE",
                    "geometricError": 1.519732,
                    "content": {
                      "uri": "mesh_1782.b3dm",
                      "boundingVolume": {
                        "region": [
                          3.1002963415155386784, -0.67530157133270896086,
                          3.1003128962385302358, -0.67528882818005597777,
                          151.18851443007588387, 194.63800783827900887
                        ]
                      }
                    }
                  },
                  {
                    "boundingVolume": {
                      "region": [
                        3.1003117654588097096, -0.67530098081128187015,
                        3.1003282443989310657, -0.67528824057062541986,
                        167.14180452656000853, 203.86363680195063353
                      ]
                    },
                    "refine": "REPLACE",
                    "geometricError": 1.523133,
                    "content": {
                      "uri": "mesh_1783.b3dm",
                      "boundingVolume": {
                        "region": [
                          3.1003117654588097096, -0.67530098081128187015,
                          3.1003282443989310657, -0.67528824057062541986,
                          167.14180452656000853, 203.86363680195063353
                        ]
                      }
                    }
                  }
                ]
              },
              {
                "boundingVolume": {
                  "region": [
                    3.1003274790168160457, -0.67529293873649942626,
                    3.1003344417656815146, -0.67528750807721615868,
                    179.31204206217080355, 195.7341230558231473
                  ]
                },
                "refine": "REPLACE",
                "geometricError": 3.056646,
                "content": {
                  "uri": "mesh_1784.b3dm",
                  "boundingVolume": {
                    "region": [
                      3.1003274790168160457, -0.67529293873649942626,
                      3.1003344417656815146, -0.67528750807721615868,
                      179.31204206217080355, 195.7341230558231473
                    ]
                  }
                },
                "children": [
                  {
                    "boundingVolume": {
                      "region": [
                        3.1003275627772395318, -0.67529290019315679761,
                        3.100334364404924159, -0.67528759567183782586,
                        179.31204175297170877, 195.13694142643362284
                      ]
                    },
                    "refine": "REPLACE",
                    "geometricError": 1.528057,
                    "content": {
                      "uri": "mesh_1785.b3dm",
                      "boundingVolume": {
                        "region": [
                          3.1003275627772395318, -0.67529290019315679761,
                          3.100334364404924159, -0.67528759567183782586,
                          179.31204175297170877, 195.13694142643362284
                        ]
                      }
                    }
                  }
                ]
              },
              {
                "boundingVolume": {
                  "region": [
                    3.1003029749228234735, -0.67531319073232254357,
                    3.1003081711033928514, -0.67530687545391643312,
                    204.73922520317137241, 212.27784519828855991
                  ]
                },
                "refine": "REPLACE",
                "geometricError": 1.484927,
                "content": {
                  "uri": "mesh_1786.b3dm",
                  "boundingVolume": {
                    "region": [
                      3.1003029749228234735, -0.67531319073232254357,
                      3.1003081711033928514, -0.67530687545391643312,
                      204.73922520317137241, 212.27784519828855991
                    ]
                  }
                }
              }
            ]
          },
          {
            "boundingVolume": {
              "region": [
                3.1002912099312589511, -0.67529124912560978267,
                3.1003594160959369042, -0.67523711832254418308,
                125.84543702658265829, 217.56935212668031454
              ]
            },
            "refine": "REPLACE",
            "geometricError": 4.209405,
            "content": {
              "uri": "mesh_1787.b3dm",
              "boundingVolume": {
                "region": [
                  3.1002912099312589511, -0.67529124912560978267,
                  3.1003594160959369042, -0.67523711832254418308,
                  125.84543702658265829, 217.56935212668031454
                ]
              }
            },
            "children": [
              {
                "boundingVolume": {
                  "region": [
                    3.100294583139294069, -0.67528974724131252128,
                    3.1003281806586269198, -0.67526163030426744616,
                    128.38756776228547096, 210.04586244001984596
                  ]
                },
                "refine": "REPLACE",
                "geometricError": 3.052463,
                "content": {
                  "uri": "mesh_1788.b3dm",
                  "boundingVolume": {
                    "region": [
                      3.100294583139294069, -0.67528974724131252128,
                      3.1003281806586269198, -0.67526163030426744616,
                      128.38756776228547096, 210.04586244001984596
                    ]
                  }
                },
                "children": [
                  {
                    "boundingVolume": {
                      "region": [
                        3.1002955359704937877, -0.67528974717221024182,
                        3.100312090517790331, -0.67527700405189750033,
                        141.55151139199733734, 183.82850418984889984
                      ]
                    },
                    "refine": "REPLACE",
                    "geometricError": 1.521159,
                    "content": {
                      "uri": "mesh_1789.b3dm",
                      "boundingVolume": {
                        "region": [
                          3.1002955359704937877, -0.67528974717221024182,
                          3.100312090517790331, -0.67527700405189750033,
                          141.55151139199733734, 183.82850418984889984
                        ]
                      }
                    }
                  },
                  {
                    "boundingVolume": {
                      "region": [
                        3.1003113260747667823, -0.67528878571982720036,
                        3.1003278048377342913, -0.67527604550922537552,
                        160.3988582557067275, 196.4210750525817275
                      ]
                    },
                    "refine": "REPLACE",
                    "geometricError": 1.524284,
                    "content": {
                      "uri": "mesh_1790.b3dm",
                      "boundingVolume": {
                        "region": [
                          3.1003113260747667823, -0.67528878571982720036,
                          3.1003278048377342913, -0.67527604550922537552,
                          160.3988582557067275, 196.4210750525817275
                        ]
                      }
                    }
                  },
                  {
                    "boundingVolume": {
                      "region": [
                        3.1002948987695542193, -0.67527572043988082218,
                        3.1003114531138091792, -0.67526297731394602231,
                        128.3875669427216053, 198.06837596371769905
                      ]
                    },
                    "refine": "REPLACE",
                    "geometricError": 1.52093,
                    "content": {
                      "uri": "mesh_1791.b3dm",
                      "boundingVolume": {
                        "region": [
                          3.1002948987695542193, -0.67527572043988082218,
                          3.1003114531138091792, -0.67526297731394602231,
                          128.3875669427216053, 198.06837596371769905
                        ]
                      }
                    }
                  },
                  {
                    "boundingVolume": {
                      "region": [
                        3.1003105307933815915, -0.67527665705543360453,
                        3.1003270093796286844, -0.67526391683895525819,
                        155.37370441667735577, 200.86641071550548077
                      ]
                    },
                    "refine": "REPLACE",
                    "geometricError": 1.525182,
                    "content": {
                      "uri": "mesh_1792.b3dm",
                      "boundingVolume": {
                        "region": [
                          3.1003105307933815915, -0.67527665705543360453,
                          3.1003270093796286844, -0.67526391683895525819,
                          155.37370441667735577, 200.86641071550548077
                        ]
                      }
                    }
                  }
                ]
              },
              {
                "boundingVolume": {
                  "region": [
                    3.1003246904794008465, -0.67528782482614257976,
                    3.1003588556711556556, -0.67526147745046671833,
                    160.50633890833705664, 213.45237238612025976
                  ]
                },
                "refine": "REPLACE",
                "geometricError": 3.05765,
                "content": {
                  "uri": "mesh_1793.b3dm",
                  "boundingVolume": {
                    "region": [
                      3.1003246904794008465, -0.67528782482614257976,
                      3.1003588556711556556, -0.67526147745046671833,
                      160.50633890833705664, 213.45237238612025976
                    ]
                  }
                },
                "children": [
                  {
                    "boundingVolume": {
                      "region": [
                        3.100326679161030885, -0.67528777899602121515,
                        3.1003431580263680623, -0.6752750386836251506,
                        172.7990493830293417, 208.6848526056855917
                      ]
                    },
                    "refine": "REPLACE",
                    "geometricError": 1.527057,
                    "content": {
                      "uri": "mesh_1794.b3dm",
                      "boundingVolume": {
                        "region": [
                          3.100326679161030885, -0.67528777899602121515,
                          3.1003431580263680623, -0.6752750386836251506,
                          172.7990493830293417, 208.6848526056855917
                        ]
                      }
                    }
                  },
                  {
                    "boundingVolume": {
                      "region": [
                        3.1003424985873810904, -0.67527985105557886136,
                        3.1003491420088704622, -0.67527466986264073068,
                        190.77332130167633295, 206.26048866007477045
                      ]
                    },
                    "refine": "REPLACE",
                    "geometricError": 1.530251,
                    "content": {
                      "uri": "mesh_1795.b3dm",
                      "boundingVolume": {
                        "region": [
                          3.1003424985873810904, -0.67527985105557886136,
                          3.1003491420088704622, -0.67527466986264073068,
                          190.77332130167633295, 206.26048866007477045
                        ]
                      }
                    }
                  },
                  {
                    "boundingVolume": {
                      "region": [
                        3.1003262058902465448, -0.67527616879204288569,
                        3.1003426845888846231, -0.67526342847127374114,
                        175.52088429126888514, 213.45237232837826014
                      ]
                    },
                    "refine": "REPLACE",
                    "geometricError": 1.527666,
                    "content": {
                      "uri": "mesh_1796.b3dm",
                      "boundingVolume": {
                        "region": [
                          3.1003262058902465448, -0.67527616879204288569,
                          3.1003426845888846231, -0.67526342847127374114,
                          175.52088429126888514, 213.45237232837826014
                        ]
                      }
                    }
                  },
                  {
                    "boundingVolume": {
                      "region": [
                        3.1003415841044423829, -0.67527490269352163921,
                        3.1003580629264075874, -0.67526216226999469239,
                        173.60630074329674244, 209.55353585071861744
                      ]
                    },
                    "refine": "REPLACE",
                    "geometricError": 1.530547,
                    "content": {
                      "uri": "mesh_1797.b3dm",
                      "boundingVolume": {
                        "region": [
                          3.1003415841044423829, -0.67527490269352163921,
                          3.1003580629264075874, -0.67526216226999469239,
                          173.60630074329674244, 209.55353585071861744
                        ]
                      }
                    }
                  }
                ]
              },
              {
                "boundingVolume": {
                  "region": [
                    3.1002929162529837548, -0.67526692423255119113,
                    3.1003264081100456728, -0.67523978113597182826,
                    125.84543869365006685, 211.6693751560524106
                  ]
                },
                "refine": "REPLACE",
                "geometricError": 3.047441,
                "content": {
                  "uri": "mesh_1798.b3dm",
                  "boundingVolume": {
                    "region": [
                      3.1002929162529837548, -0.67526692423255119113,
                      3.1003264081100456728, -0.67523978113597182826,
                      125.84543869365006685, 211.6693751560524106
                    ]
                  }
                },
                "children": [
                  {
                    "boundingVolume": {
                      "region": [
                        3.1002939418420383255, -0.67526648839430758464,
                        3.1003104960473417684, -0.67525374528089210369,
                        125.84544052183628082, 193.97738327085971832
                      ]
                    },
                    "refine": "REPLACE",
                    "geometricError": 1.522283,
                    "content": {
                      "uri": "mesh_1799.b3dm",
                      "boundingVolume": {
                        "region": [
                          3.1002939418420383255, -0.67526648839430758464,
                          3.1003104960473417684, -0.67525374528089210369,
                          125.84544052183628082, 193.97738327085971832
                        ]
                      }
                    }
                  },
                  {
                    "boundingVolume": {
                      "region": [
                        3.1003097897330884614, -0.67526411947334807895,
                        3.1003262681360639341, -0.67525137927003398008,
                        171.79933486692607403, 206.04362807981669903
                      ]
                    },
                    "refine": "REPLACE",
                    "geometricError": 1.524406,
                    "content": {
                      "uri": "mesh_1800.b3dm",
                      "boundingVolume": {
                        "region": [
                          3.1003097897330884614, -0.67526411947334807895,
                          3.1003262681360639341, -0.67525137927003398008,
                          171.79933486692607403, 206.04362807981669903
                        ]
                      }
                    }
                  },
                  {
                    "boundingVolume": {
                      "region": [
                        3.100293176000622708, -0.67525321081476219476,
                        3.100309733856479788, -0.67524040823729980509,
                        137.21574348211288452, 179.87304633855819702
                      ]
                    },
                    "refine": "REPLACE",
                    "geometricError": 1.52344,
                    "content": {
                      "uri": "mesh_1801.b3dm",
                      "boundingVolume": {
                        "region": [
                          3.100293176000622708, -0.67525321081476219476,
                          3.100309733856479788, -0.67524040823729980509,
                          137.21574348211288452, 179.87304633855819702
                        ]
                      }
                    }
                  },
                  {
                    "boundingVolume": {
                      "region": [
                        3.1003086430236854731, -0.67525295165430954114,
                        3.1003251251053396409, -0.67524015198812104011,
                        169.06203160714358091, 205.93249974679201841
                      ]
                    },
                    "refine": "REPLACE",
                    "geometricError": 1.524574,
                    "content": {
                      "uri": "mesh_1802.b3dm",
                      "boundingVolume": {
                        "region": [
                          3.1003086430236854731, -0.67525295165430954114,
                          3.1003251251053396409, -0.67524015198812104011,
                          169.06203160714358091, 205.93249974679201841
                        ]
                      }
                    }
                  }
                ]
              },
              {
                "boundingVolume": {
                  "region": [
                    3.1003245376354477969, -0.67526475182598422187,
                    3.1003577873998064973, -0.67523711832325605808,
                    160.56432444136589766, 211.72790247481316328
                  ]
                },
                "refine": "REPLACE",
                "geometricError": 3.049904,
                "content": {
                  "uri": "mesh_1803.b3dm",
                  "boundingVolume": {
                    "region": [
                      3.1003245376354477969, -0.67526475182598422187,
                      3.1003577873998064973, -0.67523711832325605808,
                      160.56432444136589766, 211.72790247481316328
                    ]
                  }
                },
                "children": [
                  {
                    "boundingVolume": {
                      "region": [
                        3.1003255274890060278, -0.67526343522670384534,
                        3.1003420060021262827, -0.67525069491880929107,
                        186.26669079717248678, 208.57267529424279928
                      ]
                    },
                    "refine": "REPLACE",
                    "geometricError": 1.526876,
                    "content": {
                      "uri": "mesh_1804.b3dm",
                      "boundingVolume": {
                        "region": [
                          3.1003255274890060278, -0.67526343522670384534,
                          3.1003420060021262827, -0.67525069491880929107,
                          186.26669079717248678, 208.57267529424279928
                        ]
                      }
                    }
                  },
                  {
                    "boundingVolume": {
                      "region": [
                        3.1003411410828594086, -0.67526412876611285885,
                        3.1003576197489532973, -0.67525138835260134496,
                        167.81806021649390459, 199.46251517254859209
                      ]
                    },
                    "refine": "REPLACE",
                    "geometricError": 1.527229,
                    "content": {
                      "uri": "mesh_1805.b3dm",
                      "boundingVolume": {
                        "region": [
                          3.1003411410828594086, -0.67526412876611285885,
                          3.1003576197489532973, -0.67525138835260134496,
                          167.81806021649390459, 199.46251517254859209
                        ]
                      }
                    }
                  },
                  {
                    "boundingVolume": {
                      "region": [
                        3.1003246585317967288, -0.67525144098016831595,
                        3.100341140714999888, -0.67523864120815502154,
                        167.12035383377224207, 209.52593244705349207
                      ]
                    },
                    "refine": "REPLACE",
                    "geometricError": 1.524394,
                    "content": {
                      "uri": "mesh_1806.b3dm",
                      "boundingVolume": {
                        "region": [
                          3.1003246585317967288, -0.67525144098016831595,
                          3.100341140714999888, -0.67523864120815502154,
                          167.12035383377224207, 209.52593244705349207
                        ]
                      }
                    }
                  },
                  {
                    "boundingVolume": {
                      "region": [
                        3.100340423375637311, -0.67525064427081016305,
                        3.1003569056927764436, -0.67523784439321821171,
                        160.56432454939931631, 200.34447591658681631
                      ]
                    },
                    "refine": "REPLACE",
                    "geometricError": 1.522777,
                    "content": {
                      "uri": "mesh_1807.b3dm",
                      "boundingVolume": {
                        "region": [
                          3.100340423375637311, -0.67525064427081016305,
                          3.1003569056927764436, -0.67523784439321821171,
                          160.56432454939931631, 200.34447591658681631
                        ]
                      }
                    }
                  }
                ]
              },
              {
                "boundingVolume": {
                  "region": [
                    3.1003411720266647045, -0.67527660586790128061,
                    3.1003477631743860954, -0.67526402205337521245,
                    206.83560434728860855, 208.19317881017923355
                  ]
                },
                "refine": "REPLACE",
                "geometricError": 1.492612,
                "content": {
                  "uri": "mesh_1808.b3dm",
                  "boundingVolume": {
                    "region": [
                      3.1003411720266647045, -0.67527660586790128061,
                      3.1003477631743860954, -0.67526402205337521245,
                      206.83560434728860855, 208.19317881017923355
                    ]
                  }
                }
              },
              {
                "boundingVolume": {
                  "region": [
                    3.1003184611914029745, -0.67525836482812351402,
                    3.10032618878689048, -0.67524600685217295304,
                    203.25347750913351774, 214.17419284116476774
                  ]
                },
                "refine": "REPLACE",
                "geometricError": 1.489468,
                "content": {
                  "uri": "mesh_1809.b3dm",
                  "boundingVolume": {
                    "region": [
                      3.1003184611914029745, -0.67525836482812351402,
                      3.10032618878689048, -0.67524600685217295304,
                      203.25347750913351774, 214.17419284116476774
                    ]
                  }
                }
              },
              {
                "boundingVolume": {
                  "region": [
                    3.1003250633220753585, -0.67526289940457506766,
                    3.1003407322843159477, -0.67524524017372289375,
                    201.72249993495643139, 214.57433709315955639
                  ]
                },
                "refine": "REPLACE",
                "geometricError": 1.489821,
                "content": {
                  "uri": "mesh_1810.b3dm",
                  "boundingVolume": {
                    "region": [
                      3.1003250633220753585, -0.67526289940457506766,
                      3.1003407322843159477, -0.67524524017372289375,
                      201.72249993495643139, 214.57433709315955639
                    ]
                  }
                }
              }
            ]
          },
          {
            "boundingVolume": {
              "region": [
                3.1003532557889217358, -0.67526757674422688282,
                3.1003950795426780118, -0.67523470479158498314,
                131.69826002046465874, 212.31382245942950249
              ]
            },
            "refine": "REPLACE",
            "geometricError": 3.851799,
            "content": {
              "uri": "mesh_1811.b3dm",
              "boundingVolume": {
                "region": [
                  3.1003532557889217358, -0.67526757674422688282,
                  3.1003950795426780118, -0.67523470479158498314,
                  131.69826002046465874, 212.31382245942950249
                ]
              }
            },
            "children": [
              {
                "boundingVolume": {
                  "region": [
                    3.1003573214489463794, -0.67526748280985715578,
                    3.1003639688854547352, -0.67526229825781647342,
                    169.26630250830203295, 180.51297799963504076
                  ]
                },
                "refine": "REPLACE",
                "geometricError": 3.068187,
                "content": {
                  "uri": "mesh_1812.b3dm",
                  "boundingVolume": {
                    "region": [
                      3.1003573214489463794, -0.67526748280985715578,
                      3.1003639688854547352, -0.67526229825781647342,
                      169.26630250830203295, 180.51297799963504076
                    ]
                  }
                },
                "children": [
                  {
                    "boundingVolume": {
                      "region": [
                        3.100357408602865128, -0.67526742470354950143,
                        3.1003638938334576736, -0.67526236683246187997,
                        169.44909636210650206, 180.09777609538286924
                      ]
                    },
                    "refine": "REPLACE",
                    "geometricError": 1.531073,
                    "content": {
                      "uri": "mesh_1813.b3dm",
                      "boundingVolume": {
                        "region": [
                          3.100357408602865128, -0.67526742470354950143,
                          3.1003638938334576736, -0.67526236683246187997,
                          169.44909636210650206, 180.09777609538286924
                        ]
                      }
                    }
                  }
                ]
              },
              {
                "boundingVolume": {
                  "region": [
                    3.1003544108025709036, -0.67526164350823003613,
                    3.1003885688318519875, -0.67523593518553481907,
                    131.69825833663344383, 203.45413297042250633
                  ]
                },
                "refine": "REPLACE",
                "geometricError": 3.051295,
                "content": {
                  "uri": "mesh_1814.b3dm",
                  "boundingVolume": {
                    "region": [
                      3.1003544108025709036, -0.67526164350823003613,
                      3.1003885688318519875, -0.67523593518553481907,
                      131.69825833663344383, 203.45413297042250633
                    ]
                  }
                },
                "children": [
                  {
                    "boundingVolume": {
                      "region": [
                        3.1003565562509960429, -0.67526121938136696166,
                        3.1003730350053051446, -0.67524847886641414796,
                        150.24885278753936291, 194.04243188910186291
                      ]
                    },
                    "refine": "REPLACE",
                    "geometricError": 1.528599,
                    "content": {
                      "uri": "mesh_1815.b3dm",
                      "boundingVolume": {
                        "region": [
                          3.1003565562509960429, -0.67526121938136696166,
                          3.1003730350053051446, -0.67524847886641414796,
                          150.24885278753936291, 194.04243188910186291
                        ]
                      }
                    }
                  },
                  {
                    "boundingVolume": {
                      "region": [
                        3.1003723090403365603, -0.6752540387386793963,
                        3.1003786360766065755, -0.675249104189929783,
                        141.87186077330261469, 163.43730571959167719
                      ]
                    },
                    "refine": "REPLACE",
                    "geometricError": 1.528532,
                    "content": {
                      "uri": "mesh_1816.b3dm",
                      "boundingVolume": {
                        "region": [
                          3.1003723090403365603, -0.6752540387386793963,
                          3.1003786360766065755, -0.675249104189929783,
                          141.87186077330261469, 163.43730571959167719
                        ]
                      }
                    }
                  },
                  {
                    "boundingVolume": {
                      "region": [
                        3.1003560491140143007, -0.67525036069926502869,
                        3.1003725315589520939, -0.67523756071718021854,
                        140.88936643116176128, 194.88917569629848003
                      ]
                    },
                    "refine": "REPLACE",
                    "geometricError": 1.523815,
                    "content": {
                      "uri": "mesh_1817.b3dm",
                      "boundingVolume": {
                        "region": [
                          3.1003560491140143007, -0.67525036069926502869,
                          3.1003725315589520939, -0.67523756071718021854,
                          140.88936643116176128, 194.88917569629848003
                        ]
                      }
                    }
                  },
                  {
                    "boundingVolume": {
                      "region": [
                        3.100371343360243781, -0.67524949345939966339,
                        3.1003878259097246151, -0.67523669337591252226,
                        131.69825989753007889, 178.49921280890703201
                      ]
                    },
                    "refine": "REPLACE",
                    "geometricError": 1.525401,
                    "content": {
                      "uri": "mesh_1818.b3dm",
                      "boundingVolume": {
                        "region": [
                          3.100371343360243781, -0.67524949345939966339,
                          3.1003878259097246151, -0.67523669337591252226,
                          131.69825989753007889, 178.49921280890703201
                        ]
                      }
                    }
                  }
                ]
              },
              {
                "boundingVolume": {
                  "region": [
                    3.1003872418897717722, -0.67524168676242257714,
                    3.1003934909022006217, -0.67523681301496407681,
                    172.86268116440623999, 182.76090313401073217
                  ]
                },
                "refine": "REPLACE",
                "geometricError": 1.540321,
                "content": {
                  "uri": "mesh_1819.b3dm",
                  "boundingVolume": {
                    "region": [
                      3.1003872418897717722, -0.67524168676242257714,
                      3.1003934909022006217, -0.67523681301496407681,
                      172.86268116440623999, 182.76090313401073217
                    ]
                  }
                }
              }
            ]
          }
        ]
      }
    ]
  },
  "asset": { "version": "1.0" }
}
